safie_mediafile/__init__.py
safie_mediafile/_client.py
safie_mediafile/_exceptions.py
safie_mediafile/_cli/__init__.py
safie_mediafile/_cli/_cli_app.py
safie_mediafile/_cli/_downloader.py
safie_mediafile/_endpoints/_device.py
safie_mediafile/_endpoints/_mediafile.py
safie_mediafile-0.1.5.dist-info/METADATA
safie_mediafile-0.1.5.dist-info/WHEEL
safie_mediafile-0.1.5.dist-info/entry_points.txt
safie_mediafile-0.1.5.dist-info/licenses/LICENSE
safie_mediafile-0.1.5.dist-info/RECORD
