Metadata-Version: 2.4
Name: safie-mediafile
Version: 0.1.5
Summary: A Python library and command-line tool for downloading media files from Safie cameras
Project-URL: Homepage, https://github.com/example/safie-mediafile
Project-URL: Issues, https://github.com/example/safie-mediafile/issues
Author-email: Example Author <author@example.com>
License-File: LICENSE
Classifier: License :: OSI Approved :: MIT License
Classifier: Operating System :: OS Independent
Classifier: Programming Language :: Python :: 3
Requires-Python: >=3.8
Requires-Dist: httpx>=0.24.0
Provides-Extra: cli
Requires-Dist: click>=8.0.0; extra == 'cli'
Requires-Dist: imageio-ffmpeg>=0.5.1; extra == 'cli'
Requires-Dist: python-dateutil>=2.9.0.post0; extra == 'cli'
Provides-Extra: dev
Requires-Dist: mypy>=1.9.0; extra == 'dev'
Requires-Dist: pytest-asyncio>=0.21.0; extra == 'dev'
Requires-Dist: pytest-cov>=4.1.0; extra == 'dev'
Requires-Dist: pytest>=7.0.0; extra == 'dev'
Requires-Dist: ruff>=0.3.0; extra == 'dev'
Requires-Dist: types-python-dateutil>=2.9.0.20241206; extra == 'dev'
